MANIFEST.in
setup.py
posix_spawn/__init__.py
posix_spawn/_impl.py
posix_spawn/_lib.py
posix_spawn.egg-info/PKG-INFO
posix_spawn.egg-info/SOURCES.txt
posix_spawn.egg-info/dependency_links.txt
posix_spawn.egg-info/not-zip-safe
posix_spawn.egg-info/requires.txt
posix_spawn.egg-info/top_level.txt
posix_spawn/__pycache__/_posix_spawn_cffi_fd40e3fbx1c29613d.c
posix_spawn/c/cdef.h
posix_spawn/c/source.c
posix_spawn/tests/__init__.py
posix_spawn/tests/test_posix_spawn.py