Metadata-Version: 1.0
Name: posix-spawn
Version: 0.2.post7
Summary: CFFI bindings to posix_spawn.
Home-page: UNKNOWN
Author: UNKNOWN
Author-email: UNKNOWN
License: MIT
Platform: UNKNOWN
